{
    "Page 1": [
        {
            "ORIGIN": "PQMZ",
            "LATENT": "NULL",
            "AGE": "NULL",
            "GENRE": "NULL"
        }
    ],
    "Page 2": [
        {
            "ORIGIN": "7THK",
            "LATENT": "NULL",
            "AGE": "NULL",
            "GENRE": "NULL"
        }
    ],
    "Page 3": [
        {
            "ORIGIN": "6AF2",
            "LATENT": "NULL",
            "AGE": "NULL",
            "GENRE": "NULL"
        }
    ],
    "Page 4": [
        {
            "ORIGIN": "6UGH",
            "LATENT": "NULL",
            "AGE": "NULL",
            "GENRE": "NULL"
        }
    ],
    "Page 5": [
        {
            "ORIGIN": "E0FR",
            "LATENT": "NULL",
            "AGE": "NULL",
            "GENRE": "NULL"
        }
    ],
    "Page 6": [
        {
            "ORIGIN": "NB2W",
            "LATENT": "NULL",
            "AGE": "NULL",
            "GENRE": "NULL"
        }
    ],
    "Page 7": [
        {
            "ORIGIN": "M63W",
            "LATENT": "NULL",
            "AGE": "NULL",
            "GENRE": "NULL"
        }
    ],
    "Page 8": [
        {
            "ORIGIN": "OYQR",
            "LATENT": "NULL",
            "AGE": "NULL",
            "GENRE": "NULL"
        }
    ],
    "Page 9": [
        {
            "ORIGIN": "RHVS",
            "LATENT": "NULL",
            "AGE": "NULL",
            "GENRE": "NULL"
        }
    ],
    "Page 10": [
        {
            "ORIGIN": "CAX6",
            "LATENT": "NULL",
            "AGE": "NULL",
            "GENRE": "NULL"
        }
    ],
    "Page 11": [
        {
            "ORIGIN": "C84W",
            "LATENT": "NULL",
            "AGE": "NULL",
            "GENRE": "NULL"
        }
    ],
    "Page 12": [
        {
            "ORIGIN": "951P",
            "LATENT": "NULL",
            "AGE": "NULL",
            "GENRE": "NULL"
        }
    ],
    "Page 13": [
        {
            "ORIGIN": "744A",
            "LATENT": "NULL",
            "AGE": "NULL",
            "GENRE": "NULL"
        }
    ],
    "Page 14": [
        {
            "ORIGIN": "I9PZ",
            "LATENT": "NULL",
            "AGE": "NULL",
            "GENRE": "NULL"
        }
    ],
    "Page 15": [
        {
            "ORIGIN": "169Y",
            "LATENT": "NULL",
            "AGE": "NULL",
            "GENRE": "NULL"
        }
    ],
    "Page 16": [
        {
            "ORIGIN": "MIVF",
            "LATENT": "NULL",
            "AGE": "NULL",
            "GENRE": "NULL"
        }
    ],
    "Page 17": [
        {
            "ORIGIN": "K4EX",
            "LATENT": "NULL",
            "AGE": "NULL",
            "GENRE": "NULL"
        }
    ],
    "Page 18": [
        {
            "ORIGIN": "I5D1",
            "LATENT": "NULL",
            "AGE": "NULL",
            "GENRE": "NULL"
        }
    ],
    "Page 19": [
        {
            "ORIGIN": "MWDB",
            "LATENT": "NULL",
            "AGE": "NULL",
            "GENRE": "NULL"
        }
    ]
}